Metadata-Version: 2.1
Name: libjonatas
Version: 0.2
Summary: Lib para projetos pessoais
Home-page: https://github.com/jona04/libjonatas
Author: Jonatas Oliveira Silva
Author-email: jonatas.iw@gmail.com
License: MIT License
Platform: UNKNOWN
Classifier: Development Status :: 2 - Pre-Alpha
Classifier: Environment :: Console
Classifier: Intended Audience :: Developers
Classifier: License :: OSI Approved :: MIT License
Classifier: Operating System :: OS Independent
Classifier: Programming Language :: Python
Classifier: Programming Language :: Python :: 3.6
Classifier: Framework :: Pytest
